skarabina/__init__.py
skarabina/barber.py
skarabina/dask_ms.py
skarabina/genesis/skarabina-base.yml
skarabina/hello.py
skarabina/main.py
skarabina/skarabina.yml
skarabina-0.1.4.dist-info/LICENSE
skarabina-0.1.4.dist-info/METADATA
skarabina-0.1.4.dist-info/WHEEL
skarabina-0.1.4.dist-info/entry_points.txt
skarabina-0.1.4.dist-info/RECORD
