Metadata-Version: 2.3
Name: skarabina
Version: 0.1.4
Summary: Skarabina (dungbeetle): An all purpose 1GC flagger
License: GPLv3
Author: Tim Molteno
Author-email: tim@elec.ac.nz
Requires-Python: >=3.10,<3.14
Classifier: License :: Other/Proprietary License
Classifier: Programming Language :: Python :: 3
Classifier: Programming Language :: Python :: 3.10
Classifier: Programming Language :: Python :: 3.11
Classifier: Programming Language :: Python :: 3.12
Classifier: Programming Language :: Python :: 3.13
Requires-Dist: dask-ms[xarray,zarr]
Requires-Dist: stimela (>=2.1.2)
Requires-Dist: zarr (>=2.0)
